are/__init__.py
are/are.py
are-2.1.0.dist-info/LICENSE
are-2.1.0.dist-info/METADATA
are-2.1.0.dist-info/WHEEL
are-2.1.0.dist-info/top_level.txt
are-2.1.0.dist-info/RECORD
